pice_core/__init__.py
pice_core/global_variables_for_test_report.py
pice_core/log_handler.py
pice_core/read_test_info.py
pice_core/can_related/__init__.py
pice_core/can_related/can_control.py
pice_core/can_related/canoe_connect.py
pice_core/can_related/kvaser_connect.py
pice_core/can_related/parse_canoe_tools.py
pice_core/cb_related/__init__.py
pice_core/cb_related/codebeamer_connect.py
pice_core/config/__init__.py
pice_core/config/report.css
pice_core/dataset_handler/__init__.py
pice_core/dataset_handler/data_set.py
pice_core/instrument_control/__init__.py
pice_core/instrument_control/battery_chroma_control.py
pice_core/instrument_control/battery_gmc_control.py
pice_core/instrument_control/battery_itech_control.py
pice_core/instrument_control/battery_korad_control.py
pice_core/instrument_control/battery_ngi.py
pice_core/instrument_control/bin_set_module_control.py
pice_core/instrument_control/read_curr_vol_module_control.py
pice_core/instrument_control/serial_control.py
pice_core/parse_config_file/__init__.py
pice_core/parse_config_file/parse_config.py
pice_core/parse_config_file/parse_yaml_case.py
pice_core/utils/__init__.py
pice_core/veristand_related/__init__.py
pice_core/veristand_related/gen_mapping.py
pice_core/veristand_related/ni_connect.py
pice_core-1.1.3.dist-info/METADATA
pice_core-1.1.3.dist-info/WHEEL
pice_core-1.1.3.dist-info/entry_points.txt
pice_core-1.1.3.dist-info/top_level.txt
pice_core-1.1.3.dist-info/RECORD
